__init__.py
episode_segmenter/__init__.py
episode_segmenter/episode_segmenter.py
episode_segmenter/event_detectors.py
episode_segmenter/event_logger.py
episode_segmenter/events.py
episode_segmenter/file_episode_segmenter.py
episode_segmenter/neem_segmenter.py
episode_segmenter/utils.py
episode_segmenter-1.0.22.dist-info/LICENSE
episode_segmenter-1.0.22.dist-info/METADATA
episode_segmenter-1.0.22.dist-info/WHEEL
episode_segmenter-1.0.22.dist-info/top_level.txt
episode_segmenter-1.0.22.dist-info/RECORD
