Metadata-Version: 2.1
Name: episode_segmenter
Version: 1.0.22
Summary: Annotates activitiy episodes represented by meshes moving in a 3D environment with the corresponding events, actions and activities.
Author-email: Abdelrhman Bassiouny <abassiou@uni-bremen.de>
License: GNU GENERAL PUBLIC LICENSE
Project-URL: Homepage, https://github.com/AbdelrhmanBassiouny/EpisodeSegmenter
Keywords: robotics,knowledge,memories,episodic,pycram
Classifier: Programming Language :: Python :: 3
Requires-Python: >=3.8
License-File: LICENSE
Requires-Dist: neem-pycram-interface==1.0.167
